{
  "id": "47e3a16a-ca89-4925-83ca-1d13ec4ccf3d",
  "prevId": "00000000-0000-0000-0000-000000000000",
  "version": "7",
  "dialect": "postgresql",
  "tables": {
    "public.accounts": {
      "name": "accounts",
      "schema": "",
      "columns": {
        "id": {
          "name": "id",
          "type": "text",
          "primaryKey": true,
          "notNull": true
        },
        "user_id": {
          "name": "user_id",
          "type": "text",
          "primaryKey": false,
          "notNull": true
        },
        "account_id": {
          "name": "account_id",
          "type": "text",
          "primaryKey": false,
          "notNull": true
        },
        "provider_id": {
          "name": "provider_id",
          "type": "text",
          "primaryKey": false,
          "notNull": true
        },
        "access_token": {
          "name": "access_token",
          "type": "text",
          "primaryKey": false,
          "notNull": false
        },
        "refresh_token": {
          "name": "refresh_token",
          "type": "text",
          "primaryKey": false,
          "notNull": false
        },
        "id_token": {
          "name": "id_token",
          "type": "text",
          "primaryKey": false,
          "notNull": false
        },
        "access_token_expires_at": {
          "name": "access_token_expires_at",
          "type": "timestamp with time zone",
          "primaryKey": false,
          "notNull": false
        },
        "refresh_token_expires_at": {
          "name": "refresh_token_expires_at",
          "type": "timestamp with time zone",
          "primaryKey": false,
          "notNull": false
        },
        "scope": {
          "name": "scope",
          "type": "text",
          "primaryKey": false,
          "notNull": false
        },
        "password": {
          "name": "password",
          "type": "text",
          "primaryKey": false,
          "notNull": false
        },
        "created_at": {
          "name": "created_at",
          "type": "timestamp with time zone",
          "primaryKey": false,
          "notNull": true,
          "default": "now()"
        },
        "updated_at": {
          "name": "updated_at",
          "type": "timestamp with time zone",
          "primaryKey": false,
          "notNull": true,
          "default": "now()"
        }
      },
      "indexes": {
        "accounts_user_idx": {
          "name": "accounts_user_idx",
          "columns": [
            {
              "expression": "user_id",
              "isExpression": false,
              "asc": true,
              "nulls": "last"
            }
          ],
          "isUnique": false,
          "concurrently": false,
          "method": "btree",
          "with": {}
        },
        "accounts_provider_account_idx": {
          "name": "accounts_provider_account_idx",
          "columns": [
            {
              "expression": "provider_id",
              "isExpression": false,
              "asc": true,
              "nulls": "last"
            },
            {
              "expression": "account_id",
              "isExpression": false,
              "asc": true,
              "nulls": "last"
            }
          ],
          "isUnique": true,
          "concurrently": false,
          "method": "btree",
          "with": {}
        }
      },
      "foreignKeys": {
        "accounts_user_id_users_id_fk": {
          "name": "accounts_user_id_users_id_fk",
          "tableFrom": "accounts",
          "tableTo": "users",
          "columnsFrom": [
            "user_id"
          ],
          "columnsTo": [
            "id"
          ],
          "onDelete": "cascade",
          "onUpdate": "no action"
        }
      },
      "compositePrimaryKeys": {},
      "uniqueConstraints": {},
      "policies": {},
      "checkConstraints": {},
      "isRLSEnabled": false
    },
    "public.admin_audit_log": {
      "name": "admin_audit_log",
      "schema": "",
      "columns": {
        "id": {
          "name": "id",
          "type": "uuid",
          "primaryKey": true,
          "notNull": true,
          "default": "gen_random_uuid()"
        },
        "actor_user_id": {
          "name": "actor_user_id",
          "type": "text",
          "primaryKey": false,
          "notNull": true
        },
        "action": {
          "name": "action",
          "type": "text",
          "primaryKey": false,
          "notNull": true
        },
        "target_tenant_id": {
          "name": "target_tenant_id",
          "type": "uuid",
          "primaryKey": false,
          "notNull": false
        },
        "target_user_id": {
          "name": "target_user_id",
          "type": "text",
          "primaryKey": false,
          "notNull": false
        },
        "metadata": {
          "name": "metadata",
          "type": "jsonb",
          "primaryKey": false,
          "notNull": false
        },
        "ip_address": {
          "name": "ip_address",
          "type": "text",
          "primaryKey": false,
          "notNull": false
        },
        "created_at": {
          "name": "created_at",
          "type": "timestamp with time zone",
          "primaryKey": false,
          "notNull": true,
          "default": "now()"
        }
      },
      "indexes": {},
      "foreignKeys": {
        "admin_audit_log_actor_user_id_users_id_fk": {
          "name": "admin_audit_log_actor_user_id_users_id_fk",
          "tableFrom": "admin_audit_log",
          "tableTo": "users",
          "columnsFrom": [
            "actor_user_id"
          ],
          "columnsTo": [
            "id"
          ],
          "onDelete": "set null",
          "onUpdate": "no action"
        },
        "admin_audit_log_target_tenant_id_tenants_id_fk": {
          "name": "admin_audit_log_target_tenant_id_tenants_id_fk",
          "tableFrom": "admin_audit_log",
          "tableTo": "tenants",
          "columnsFrom": [
            "target_tenant_id"
          ],
          "columnsTo": [
            "id"
          ],
          "onDelete": "set null",
          "onUpdate": "no action"
        },
        "admin_audit_log_target_user_id_users_id_fk": {
          "name": "admin_audit_log_target_user_id_users_id_fk",
          "tableFrom": "admin_audit_log",
          "tableTo": "users",
          "columnsFrom": [
            "target_user_id"
          ],
          "columnsTo": [
            "id"
          ],
          "onDelete": "set null",
          "onUpdate": "no action"
        }
      },
      "compositePrimaryKeys": {},
      "uniqueConstraints": {},
      "policies": {},
      "checkConstraints": {},
      "isRLSEnabled": false
    },
    "public.components_nomenclature": {
      "name": "components_nomenclature",
      "schema": "",
      "columns": {
        "id": {
          "name": "id",
          "type": "uuid",
          "primaryKey": true,
          "notNull": true,
          "default": "gen_random_uuid()"
        },
        "tenant_id": {
          "name": "tenant_id",
          "type": "uuid",
          "primaryKey": false,
          "notNull": true
        },
        "syllabus_code": {
          "name": "syllabus_code",
          "type": "text",
          "primaryKey": false,
          "notNull": true
        },
        "syllabus_name": {
          "name": "syllabus_name",
          "type": "text",
          "primaryKey": false,
          "notNull": false
        },
        "component_code": {
          "name": "component_code",
          "type": "text",
          "primaryKey": false,
          "notNull": true
        },
        "component_name": {
          "name": "component_name",
          "type": "text",
          "primaryKey": false,
          "notNull": true
        },
        "created_at": {
          "name": "created_at",
          "type": "timestamp with time zone",
          "primaryKey": false,
          "notNull": true,
          "default": "now()"
        }
      },
      "indexes": {
        "comp_nom_tenant_sub_comp_idx": {
          "name": "comp_nom_tenant_sub_comp_idx",
          "columns": [
            {
              "expression": "tenant_id",
              "isExpression": false,
              "asc": true,
              "nulls": "last"
            },
            {
              "expression": "syllabus_code",
              "isExpression": false,
              "asc": true,
              "nulls": "last"
            },
            {
              "expression": "component_code",
              "isExpression": false,
              "asc": true,
              "nulls": "last"
            }
          ],
          "isUnique": true,
          "concurrently": false,
          "method": "btree",
          "with": {}
        }
      },
      "foreignKeys": {
        "components_nomenclature_tenant_id_tenants_id_fk": {
          "name": "components_nomenclature_tenant_id_tenants_id_fk",
          "tableFrom": "components_nomenclature",
          "tableTo": "tenants",
          "columnsFrom": [
            "tenant_id"
          ],
          "columnsTo": [
            "id"
          ],
          "onDelete": "cascade",
          "onUpdate": "no action"
        }
      },
      "compositePrimaryKeys": {},
      "uniqueConstraints": {},
      "policies": {},
      "checkConstraints": {},
      "isRLSEnabled": false
    },
    "public.comprehensive_results": {
      "name": "comprehensive_results",
      "schema": "",
      "columns": {
        "id": {
          "name": "id",
          "type": "uuid",
          "primaryKey": true,
          "notNull": true,
          "default": "gen_random_uuid()"
        },
        "tenant_id": {
          "name": "tenant_id",
          "type": "uuid",
          "primaryKey": false,
          "notNull": true
        },
        "upload_id": {
          "name": "upload_id",
          "type": "uuid",
          "primaryKey": false,
          "notNull": true
        },
        "syllabus": {
          "name": "syllabus",
          "type": "text",
          "primaryKey": false,
          "notNull": true
        },
        "option_code": {
          "name": "option_code",
          "type": "text",
          "primaryKey": false,
          "notNull": false
        },
        "centre_number": {
          "name": "centre_number",
          "type": "text",
          "primaryKey": false,
          "notNull": false
        },
        "candidate_number": {
          "name": "candidate_number",
          "type": "text",
          "primaryKey": false,
          "notNull": true
        },
        "candidate_name": {
          "name": "candidate_name",
          "type": "text",
          "primaryKey": false,
          "notNull": true
        },
        "component_data": {
          "name": "component_data",
          "type": "jsonb",
          "primaryKey": false,
          "notNull": false
        },
        "final_marks": {
          "name": "final_marks",
          "type": "jsonb",
          "primaryKey": false,
          "notNull": false
        },
        "syllabus_total": {
          "name": "syllabus_total",
          "type": "real",
          "primaryKey": false,
          "notNull": false
        },
        "syllabus_grade": {
          "name": "syllabus_grade",
          "type": "text",
          "primaryKey": false,
          "notNull": false
        },
        "sheet_name": {
          "name": "sheet_name",
          "type": "text",
          "primaryKey": false,
          "notNull": false
        },
        "period": {
          "name": "period",
          "type": "date",
          "primaryKey": false,
          "notNull": false
        },
        "exam_type": {
          "name": "exam_type",
          "type": "exam_type",
          "typeSchema": "public",
          "primaryKey": false,
          "notNull": true
        },
        "raw_data": {
          "name": "raw_data",
          "type": "jsonb",
          "primaryKey": false,
          "notNull": false
        },
        "processed_at": {
          "name": "processed_at",
          "type": "timestamp with time zone",
          "primaryKey": false,
          "notNull": true,
          "default": "now()"
        }
      },
      "indexes": {
        "comp_results_tenant_idx": {
          "name": "comp_results_tenant_idx",
          "columns": [
            {
              "expression": "tenant_id",
              "isExpression": false,
              "asc": true,
              "nulls": "last"
            }
          ],
          "isUnique": false,
          "concurrently": false,
          "method": "btree",
          "with": {}
        },
        "comp_results_tenant_candidate_idx": {
          "name": "comp_results_tenant_candidate_idx",
          "columns": [
            {
              "expression": "tenant_id",
              "isExpression": false,
              "asc": true,
              "nulls": "last"
            },
            {
              "expression": "candidate_number",
              "isExpression": false,
              "asc": true,
              "nulls": "last"
            },
            {
              "expression": "candidate_name",
              "isExpression": false,
              "asc": true,
              "nulls": "last"
            }
          ],
          "isUnique": false,
          "concurrently": false,
          "method": "btree",
          "with": {}
        },
        "comp_results_tenant_syllabus_idx": {
          "name": "comp_results_tenant_syllabus_idx",
          "columns": [
            {
              "expression": "tenant_id",
              "isExpression": false,
              "asc": true,
              "nulls": "last"
            },
            {
              "expression": "syllabus",
              "isExpression": false,
              "asc": true,
              "nulls": "last"
            },
            {
              "expression": "period",
              "isExpression": false,
              "asc": true,
              "nulls": "last"
            }
          ],
          "isUnique": false,
          "concurrently": false,
          "method": "btree",
          "with": {}
        }
      },
      "foreignKeys": {
        "comprehensive_results_tenant_id_tenants_id_fk": {
          "name": "comprehensive_results_tenant_id_tenants_id_fk",
          "tableFrom": "comprehensive_results",
          "tableTo": "tenants",
          "columnsFrom": [
            "tenant_id"
          ],
          "columnsTo": [
            "id"
          ],
          "onDelete": "cascade",
          "onUpdate": "no action"
        },
        "comprehensive_results_upload_id_uploads_id_fk": {
          "name": "comprehensive_results_upload_id_uploads_id_fk",
          "tableFrom": "comprehensive_results",
          "tableTo": "uploads",
          "columnsFrom": [
            "upload_id"
          ],
          "columnsTo": [
            "id"
          ],
          "onDelete": "cascade",
          "onUpdate": "no action"
        }
      },
      "compositePrimaryKeys": {},
      "uniqueConstraints": {},
      "policies": {},
      "checkConstraints": {},
      "isRLSEnabled": false
    },
    "public.credit_balances": {
      "name": "credit_balances",
      "schema": "",
      "columns": {
        "tenant_id": {
          "name": "tenant_id",
          "type": "uuid",
          "primaryKey": true,
          "notNull": true
        },
        "balance": {
          "name": "balance",
          "type": "integer",
          "primaryKey": false,
          "notNull": true,
          "default": 0
        },
        "lifetime_purchased": {
          "name": "lifetime_purchased",
          "type": "integer",
          "primaryKey": false,
          "notNull": true,
          "default": 0
        },
        "lifetime_spent": {
          "name": "lifetime_spent",
          "type": "integer",
          "primaryKey": false,
          "notNull": true,
          "default": 0
        },
        "updated_at": {
          "name": "updated_at",
          "type": "timestamp with time zone",
          "primaryKey": false,
          "notNull": true,
          "default": "now()"
        }
      },
      "indexes": {},
      "foreignKeys": {
        "credit_balances_tenant_id_tenants_id_fk": {
          "name": "credit_balances_tenant_id_tenants_id_fk",
          "tableFrom": "credit_balances",
          "tableTo": "tenants",
          "columnsFrom": [
            "tenant_id"
          ],
          "columnsTo": [
            "id"
          ],
          "onDelete": "cascade",
          "onUpdate": "no action"
        }
      },
      "compositePrimaryKeys": {},
      "uniqueConstraints": {},
      "policies": {},
      "checkConstraints": {},
      "isRLSEnabled": false
    },
    "public.credit_purchases": {
      "name": "credit_purchases",
      "schema": "",
      "columns": {
        "id": {
          "name": "id",
          "type": "uuid",
          "primaryKey": true,
          "notNull": true,
          "default": "gen_random_uuid()"
        },
        "tenant_id": {
          "name": "tenant_id",
          "type": "uuid",
          "primaryKey": false,
          "notNull": true
        },
        "initiated_by_user_id": {
          "name": "initiated_by_user_id",
          "type": "text",
          "primaryKey": false,
          "notNull": true
        },
        "pack_id": {
          "name": "pack_id",
          "type": "text",
          "primaryKey": false,
          "notNull": true
        },
        "credits_to_credit": {
          "name": "credits_to_credit",
          "type": "integer",
          "primaryKey": false,
          "notNull": true
        },
        "amount_kobo": {
          "name": "amount_kobo",
          "type": "integer",
          "primaryKey": false,
          "notNull": true
        },
        "currency": {
          "name": "currency",
          "type": "text",
          "primaryKey": false,
          "notNull": true,
          "default": "'GHS'"
        },
        "paystack_reference": {
          "name": "paystack_reference",
          "type": "text",
          "primaryKey": false,
          "notNull": true
        },
        "paystack_access_code": {
          "name": "paystack_access_code",
          "type": "text",
          "primaryKey": false,
          "notNull": false
        },
        "paystack_authorization_url": {
          "name": "paystack_authorization_url",
          "type": "text",
          "primaryKey": false,
          "notNull": false
        },
        "status": {
          "name": "status",
          "type": "purchase_status",
          "typeSchema": "public",
          "primaryKey": false,
          "notNull": true,
          "default": "'initialized'"
        },
        "paid_at": {
          "name": "paid_at",
          "type": "timestamp with time zone",
          "primaryKey": false,
          "notNull": false
        },
        "raw_response": {
          "name": "raw_response",
          "type": "jsonb",
          "primaryKey": false,
          "notNull": false
        },
        "created_at": {
          "name": "created_at",
          "type": "timestamp with time zone",
          "primaryKey": false,
          "notNull": true,
          "default": "now()"
        },
        "updated_at": {
          "name": "updated_at",
          "type": "timestamp with time zone",
          "primaryKey": false,
          "notNull": true,
          "default": "now()"
        }
      },
      "indexes": {
        "credit_purchases_tenant_idx": {
          "name": "credit_purchases_tenant_idx",
          "columns": [
            {
              "expression": "tenant_id",
              "isExpression": false,
              "asc": true,
              "nulls": "last"
            },
            {
              "expression": "created_at",
              "isExpression": false,
              "asc": true,
              "nulls": "last"
            }
          ],
          "isUnique": false,
          "concurrently": false,
          "method": "btree",
          "with": {}
        },
        "credit_purchases_ref_idx": {
          "name": "credit_purchases_ref_idx",
          "columns": [
            {
              "expression": "paystack_reference",
              "isExpression": false,
              "asc": true,
              "nulls": "last"
            }
          ],
          "isUnique": true,
          "concurrently": false,
          "method": "btree",
          "with": {}
        }
      },
      "foreignKeys": {
        "credit_purchases_tenant_id_tenants_id_fk": {
          "name": "credit_purchases_tenant_id_tenants_id_fk",
          "tableFrom": "credit_purchases",
          "tableTo": "tenants",
          "columnsFrom": [
            "tenant_id"
          ],
          "columnsTo": [
            "id"
          ],
          "onDelete": "cascade",
          "onUpdate": "no action"
        },
        "credit_purchases_initiated_by_user_id_users_id_fk": {
          "name": "credit_purchases_initiated_by_user_id_users_id_fk",
          "tableFrom": "credit_purchases",
          "tableTo": "users",
          "columnsFrom": [
            "initiated_by_user_id"
          ],
          "columnsTo": [
            "id"
          ],
          "onDelete": "set null",
          "onUpdate": "no action"
        }
      },
      "compositePrimaryKeys": {},
      "uniqueConstraints": {
        "credit_purchases_paystack_reference_unique": {
          "name": "credit_purchases_paystack_reference_unique",
          "nullsNotDistinct": false,
          "columns": [
            "paystack_reference"
          ]
        }
      },
      "policies": {},
      "checkConstraints": {},
      "isRLSEnabled": false
    },
    "public.credit_transactions": {
      "name": "credit_transactions",
      "schema": "",
      "columns": {
        "id": {
          "name": "id",
          "type": "uuid",
          "primaryKey": true,
          "notNull": true,
          "default": "gen_random_uuid()"
        },
        "tenant_id": {
          "name": "tenant_id",
          "type": "uuid",
          "primaryKey": false,
          "notNull": true
        },
        "type": {
          "name": "type",
          "type": "credit_txn_type",
          "typeSchema": "public",
          "primaryKey": false,
          "notNull": true
        },
        "amount": {
          "name": "amount",
          "type": "integer",
          "primaryKey": false,
          "notNull": true
        },
        "balance_after": {
          "name": "balance_after",
          "type": "integer",
          "primaryKey": false,
          "notNull": true
        },
        "note": {
          "name": "note",
          "type": "text",
          "primaryKey": false,
          "notNull": false
        },
        "purchase_id": {
          "name": "purchase_id",
          "type": "uuid",
          "primaryKey": false,
          "notNull": false
        },
        "upload_id": {
          "name": "upload_id",
          "type": "uuid",
          "primaryKey": false,
          "notNull": false
        },
        "actor_user_id": {
          "name": "actor_user_id",
          "type": "text",
          "primaryKey": false,
          "notNull": false
        },
        "created_at": {
          "name": "created_at",
          "type": "timestamp with time zone",
          "primaryKey": false,
          "notNull": true,
          "default": "now()"
        }
      },
      "indexes": {
        "credit_txn_tenant_idx": {
          "name": "credit_txn_tenant_idx",
          "columns": [
            {
              "expression": "tenant_id",
              "isExpression": false,
              "asc": true,
              "nulls": "last"
            },
            {
              "expression": "created_at",
              "isExpression": false,
              "asc": true,
              "nulls": "last"
            }
          ],
          "isUnique": false,
          "concurrently": false,
          "method": "btree",
          "with": {}
        }
      },
      "foreignKeys": {
        "credit_transactions_tenant_id_tenants_id_fk": {
          "name": "credit_transactions_tenant_id_tenants_id_fk",
          "tableFrom": "credit_transactions",
          "tableTo": "tenants",
          "columnsFrom": [
            "tenant_id"
          ],
          "columnsTo": [
            "id"
          ],
          "onDelete": "cascade",
          "onUpdate": "no action"
        },
        "credit_transactions_purchase_id_credit_purchases_id_fk": {
          "name": "credit_transactions_purchase_id_credit_purchases_id_fk",
          "tableFrom": "credit_transactions",
          "tableTo": "credit_purchases",
          "columnsFrom": [
            "purchase_id"
          ],
          "columnsTo": [
            "id"
          ],
          "onDelete": "set null",
          "onUpdate": "no action"
        },
        "credit_transactions_actor_user_id_users_id_fk": {
          "name": "credit_transactions_actor_user_id_users_id_fk",
          "tableFrom": "credit_transactions",
          "tableTo": "users",
          "columnsFrom": [
            "actor_user_id"
          ],
          "columnsTo": [
            "id"
          ],
          "onDelete": "set null",
          "onUpdate": "no action"
        }
      },
      "compositePrimaryKeys": {},
      "uniqueConstraints": {},
      "policies": {},
      "checkConstraints": {},
      "isRLSEnabled": false
    },
    "public.impersonation_sessions": {
      "name": "impersonation_sessions",
      "schema": "",
      "columns": {
        "id": {
          "name": "id",
          "type": "uuid",
          "primaryKey": true,
          "notNull": true,
          "default": "gen_random_uuid()"
        },
        "session_id": {
          "name": "session_id",
          "type": "text",
          "primaryKey": false,
          "notNull": true
        },
        "impersonated_user_id": {
          "name": "impersonated_user_id",
          "type": "text",
          "primaryKey": false,
          "notNull": true
        },
        "started_by_id": {
          "name": "started_by_id",
          "type": "text",
          "primaryKey": false,
          "notNull": true
        },
        "reason": {
          "name": "reason",
          "type": "text",
          "primaryKey": false,
          "notNull": false
        },
        "started_at": {
          "name": "started_at",
          "type": "timestamp with time zone",
          "primaryKey": false,
          "notNull": true,
          "default": "now()"
        },
        "ended_at": {
          "name": "ended_at",
          "type": "timestamp with time zone",
          "primaryKey": false,
          "notNull": false
        }
      },
      "indexes": {
        "impersonation_session_idx": {
          "name": "impersonation_session_idx",
          "columns": [
            {
              "expression": "session_id",
              "isExpression": false,
              "asc": true,
              "nulls": "last"
            }
          ],
          "isUnique": false,
          "concurrently": false,
          "method": "btree",
          "with": {}
        }
      },
      "foreignKeys": {
        "impersonation_sessions_session_id_sessions_id_fk": {
          "name": "impersonation_sessions_session_id_sessions_id_fk",
          "tableFrom": "impersonation_sessions",
          "tableTo": "sessions",
          "columnsFrom": [
            "session_id"
          ],
          "columnsTo": [
            "id"
          ],
          "onDelete": "cascade",
          "onUpdate": "no action"
        },
        "impersonation_sessions_impersonated_user_id_users_id_fk": {
          "name": "impersonation_sessions_impersonated_user_id_users_id_fk",
          "tableFrom": "impersonation_sessions",
          "tableTo": "users",
          "columnsFrom": [
            "impersonated_user_id"
          ],
          "columnsTo": [
            "id"
          ],
          "onDelete": "cascade",
          "onUpdate": "no action"
        },
        "impersonation_sessions_started_by_id_users_id_fk": {
          "name": "impersonation_sessions_started_by_id_users_id_fk",
          "tableFrom": "impersonation_sessions",
          "tableTo": "users",
          "columnsFrom": [
            "started_by_id"
          ],
          "columnsTo": [
            "id"
          ],
          "onDelete": "cascade",
          "onUpdate": "no action"
        }
      },
      "compositePrimaryKeys": {},
      "uniqueConstraints": {},
      "policies": {},
      "checkConstraints": {},
      "isRLSEnabled": false
    },
    "public.sessions": {
      "name": "sessions",
      "schema": "",
      "columns": {
        "id": {
          "name": "id",
          "type": "text",
          "primaryKey": true,
          "notNull": true
        },
        "user_id": {
          "name": "user_id",
          "type": "text",
          "primaryKey": false,
          "notNull": true
        },
        "token": {
          "name": "token",
          "type": "text",
          "primaryKey": false,
          "notNull": true
        },
        "expires_at": {
          "name": "expires_at",
          "type": "timestamp with time zone",
          "primaryKey": false,
          "notNull": true
        },
        "ip_address": {
          "name": "ip_address",
          "type": "text",
          "primaryKey": false,
          "notNull": false
        },
        "user_agent": {
          "name": "user_agent",
          "type": "text",
          "primaryKey": false,
          "notNull": false
        },
        "active_tenant_id": {
          "name": "active_tenant_id",
          "type": "uuid",
          "primaryKey": false,
          "notNull": false
        },
        "created_at": {
          "name": "created_at",
          "type": "timestamp with time zone",
          "primaryKey": false,
          "notNull": true,
          "default": "now()"
        },
        "updated_at": {
          "name": "updated_at",
          "type": "timestamp with time zone",
          "primaryKey": false,
          "notNull": true,
          "default": "now()"
        }
      },
      "indexes": {
        "sessions_user_idx": {
          "name": "sessions_user_idx",
          "columns": [
            {
              "expression": "user_id",
              "isExpression": false,
              "asc": true,
              "nulls": "last"
            }
          ],
          "isUnique": false,
          "concurrently": false,
          "method": "btree",
          "with": {}
        },
        "sessions_token_idx": {
          "name": "sessions_token_idx",
          "columns": [
            {
              "expression": "token",
              "isExpression": false,
              "asc": true,
              "nulls": "last"
            }
          ],
          "isUnique": false,
          "concurrently": false,
          "method": "btree",
          "with": {}
        }
      },
      "foreignKeys": {
        "sessions_user_id_users_id_fk": {
          "name": "sessions_user_id_users_id_fk",
          "tableFrom": "sessions",
          "tableTo": "users",
          "columnsFrom": [
            "user_id"
          ],
          "columnsTo": [
            "id"
          ],
          "onDelete": "cascade",
          "onUpdate": "no action"
        },
        "sessions_active_tenant_id_tenants_id_fk": {
          "name": "sessions_active_tenant_id_tenants_id_fk",
          "tableFrom": "sessions",
          "tableTo": "tenants",
          "columnsFrom": [
            "active_tenant_id"
          ],
          "columnsTo": [
            "id"
          ],
          "onDelete": "set null",
          "onUpdate": "no action"
        }
      },
      "compositePrimaryKeys": {},
      "uniqueConstraints": {
        "sessions_token_unique": {
          "name": "sessions_token_unique",
          "nullsNotDistinct": false,
          "columns": [
            "token"
          ]
        }
      },
      "policies": {},
      "checkConstraints": {},
      "isRLSEnabled": false
    },
    "public.summary_results": {
      "name": "summary_results",
      "schema": "",
      "columns": {
        "id": {
          "name": "id",
          "type": "uuid",
          "primaryKey": true,
          "notNull": true,
          "default": "gen_random_uuid()"
        },
        "tenant_id": {
          "name": "tenant_id",
          "type": "uuid",
          "primaryKey": false,
          "notNull": true
        },
        "upload_id": {
          "name": "upload_id",
          "type": "uuid",
          "primaryKey": false,
          "notNull": true
        },
        "candidate_number": {
          "name": "candidate_number",
          "type": "text",
          "primaryKey": false,
          "notNull": true
        },
        "candidate_name": {
          "name": "candidate_name",
          "type": "text",
          "primaryKey": false,
          "notNull": true
        },
        "subject": {
          "name": "subject",
          "type": "text",
          "primaryKey": false,
          "notNull": true
        },
        "syllabus_code": {
          "name": "syllabus_code",
          "type": "text",
          "primaryKey": false,
          "notNull": false
        },
        "grade": {
          "name": "grade",
          "type": "text",
          "primaryKey": false,
          "notNull": true
        },
        "qualification": {
          "name": "qualification",
          "type": "text",
          "primaryKey": false,
          "notNull": false
        },
        "exam_type": {
          "name": "exam_type",
          "type": "exam_type",
          "typeSchema": "public",
          "primaryKey": false,
          "notNull": true
        },
        "period": {
          "name": "period",
          "type": "date",
          "primaryKey": false,
          "notNull": false
        },
        "processed_at": {
          "name": "processed_at",
          "type": "timestamp with time zone",
          "primaryKey": false,
          "notNull": true,
          "default": "now()"
        }
      },
      "indexes": {
        "sum_results_tenant_idx": {
          "name": "sum_results_tenant_idx",
          "columns": [
            {
              "expression": "tenant_id",
              "isExpression": false,
              "asc": true,
              "nulls": "last"
            }
          ],
          "isUnique": false,
          "concurrently": false,
          "method": "btree",
          "with": {}
        },
        "sum_results_tenant_candidate_idx": {
          "name": "sum_results_tenant_candidate_idx",
          "columns": [
            {
              "expression": "tenant_id",
              "isExpression": false,
              "asc": true,
              "nulls": "last"
            },
            {
              "expression": "candidate_number",
              "isExpression": false,
              "asc": true,
              "nulls": "last"
            }
          ],
          "isUnique": false,
          "concurrently": false,
          "method": "btree",
          "with": {}
        },
        "sum_results_tenant_period_idx": {
          "name": "sum_results_tenant_period_idx",
          "columns": [
            {
              "expression": "tenant_id",
              "isExpression": false,
              "asc": true,
              "nulls": "last"
            },
            {
              "expression": "period",
              "isExpression": false,
              "asc": true,
              "nulls": "last"
            },
            {
              "expression": "exam_type",
              "isExpression": false,
              "asc": true,
              "nulls": "last"
            }
          ],
          "isUnique": false,
          "concurrently": false,
          "method": "btree",
          "with": {}
        }
      },
      "foreignKeys": {
        "summary_results_tenant_id_tenants_id_fk": {
          "name": "summary_results_tenant_id_tenants_id_fk",
          "tableFrom": "summary_results",
          "tableTo": "tenants",
          "columnsFrom": [
            "tenant_id"
          ],
          "columnsTo": [
            "id"
          ],
          "onDelete": "cascade",
          "onUpdate": "no action"
        },
        "summary_results_upload_id_uploads_id_fk": {
          "name": "summary_results_upload_id_uploads_id_fk",
          "tableFrom": "summary_results",
          "tableTo": "uploads",
          "columnsFrom": [
            "upload_id"
          ],
          "columnsTo": [
            "id"
          ],
          "onDelete": "cascade",
          "onUpdate": "no action"
        }
      },
      "compositePrimaryKeys": {},
      "uniqueConstraints": {},
      "policies": {},
      "checkConstraints": {},
      "isRLSEnabled": false
    },
    "public.syllabus_nomenclature": {
      "name": "syllabus_nomenclature",
      "schema": "",
      "columns": {
        "id": {
          "name": "id",
          "type": "uuid",
          "primaryKey": true,
          "notNull": true,
          "default": "gen_random_uuid()"
        },
        "tenant_id": {
          "name": "tenant_id",
          "type": "uuid",
          "primaryKey": false,
          "notNull": true
        },
        "syllabus_code": {
          "name": "syllabus_code",
          "type": "text",
          "primaryKey": false,
          "notNull": true
        },
        "syllabus_name": {
          "name": "syllabus_name",
          "type": "text",
          "primaryKey": false,
          "notNull": true
        },
        "created_at": {
          "name": "created_at",
          "type": "timestamp with time zone",
          "primaryKey": false,
          "notNull": true,
          "default": "now()"
        }
      },
      "indexes": {
        "syllabus_nom_tenant_code_idx": {
          "name": "syllabus_nom_tenant_code_idx",
          "columns": [
            {
              "expression": "tenant_id",
              "isExpression": false,
              "asc": true,
              "nulls": "last"
            },
            {
              "expression": "syllabus_code",
              "isExpression": false,
              "asc": true,
              "nulls": "last"
            }
          ],
          "isUnique": true,
          "concurrently": false,
          "method": "btree",
          "with": {}
        }
      },
      "foreignKeys": {
        "syllabus_nomenclature_tenant_id_tenants_id_fk": {
          "name": "syllabus_nomenclature_tenant_id_tenants_id_fk",
          "tableFrom": "syllabus_nomenclature",
          "tableTo": "tenants",
          "columnsFrom": [
            "tenant_id"
          ],
          "columnsTo": [
            "id"
          ],
          "onDelete": "cascade",
          "onUpdate": "no action"
        }
      },
      "compositePrimaryKeys": {},
      "uniqueConstraints": {},
      "policies": {},
      "checkConstraints": {},
      "isRLSEnabled": false
    },
    "public.teacher_subjects": {
      "name": "teacher_subjects",
      "schema": "",
      "columns": {
        "id": {
          "name": "id",
          "type": "uuid",
          "primaryKey": true,
          "notNull": true,
          "default": "gen_random_uuid()"
        },
        "tenant_id": {
          "name": "tenant_id",
          "type": "uuid",
          "primaryKey": false,
          "notNull": true
        },
        "teacher_id": {
          "name": "teacher_id",
          "type": "uuid",
          "primaryKey": false,
          "notNull": true
        },
        "syllabus_code": {
          "name": "syllabus_code",
          "type": "text",
          "primaryKey": false,
          "notNull": true
        },
        "exam_type": {
          "name": "exam_type",
          "type": "exam_type",
          "typeSchema": "public",
          "primaryKey": false,
          "notNull": true
        },
        "is_primary_teacher": {
          "name": "is_primary_teacher",
          "type": "boolean",
          "primaryKey": false,
          "notNull": true,
          "default": false
        },
        "assigned_at": {
          "name": "assigned_at",
          "type": "timestamp with time zone",
          "primaryKey": false,
          "notNull": true,
          "default": "now()"
        }
      },
      "indexes": {
        "teacher_subjects_tenant_teacher_idx": {
          "name": "teacher_subjects_tenant_teacher_idx",
          "columns": [
            {
              "expression": "tenant_id",
              "isExpression": false,
              "asc": true,
              "nulls": "last"
            },
            {
              "expression": "teacher_id",
              "isExpression": false,
              "asc": true,
              "nulls": "last"
            }
          ],
          "isUnique": false,
          "concurrently": false,
          "method": "btree",
          "with": {}
        },
        "teacher_subjects_unique_idx": {
          "name": "teacher_subjects_unique_idx",
          "columns": [
            {
              "expression": "teacher_id",
              "isExpression": false,
              "asc": true,
              "nulls": "last"
            },
            {
              "expression": "syllabus_code",
              "isExpression": false,
              "asc": true,
              "nulls": "last"
            },
            {
              "expression": "exam_type",
              "isExpression": false,
              "asc": true,
              "nulls": "last"
            }
          ],
          "isUnique": true,
          "concurrently": false,
          "method": "btree",
          "with": {}
        }
      },
      "foreignKeys": {
        "teacher_subjects_tenant_id_tenants_id_fk": {
          "name": "teacher_subjects_tenant_id_tenants_id_fk",
          "tableFrom": "teacher_subjects",
          "tableTo": "tenants",
          "columnsFrom": [
            "tenant_id"
          ],
          "columnsTo": [
            "id"
          ],
          "onDelete": "cascade",
          "onUpdate": "no action"
        },
        "teacher_subjects_teacher_id_teachers_id_fk": {
          "name": "teacher_subjects_teacher_id_teachers_id_fk",
          "tableFrom": "teacher_subjects",
          "tableTo": "teachers",
          "columnsFrom": [
            "teacher_id"
          ],
          "columnsTo": [
            "id"
          ],
          "onDelete": "cascade",
          "onUpdate": "no action"
        }
      },
      "compositePrimaryKeys": {},
      "uniqueConstraints": {},
      "policies": {},
      "checkConstraints": {},
      "isRLSEnabled": false
    },
    "public.teachers": {
      "name": "teachers",
      "schema": "",
      "columns": {
        "id": {
          "name": "id",
          "type": "uuid",
          "primaryKey": true,
          "notNull": true,
          "default": "gen_random_uuid()"
        },
        "tenant_id": {
          "name": "tenant_id",
          "type": "uuid",
          "primaryKey": false,
          "notNull": true
        },
        "first_name": {
          "name": "first_name",
          "type": "text",
          "primaryKey": false,
          "notNull": true
        },
        "last_name": {
          "name": "last_name",
          "type": "text",
          "primaryKey": false,
          "notNull": true
        },
        "email": {
          "name": "email",
          "type": "text",
          "primaryKey": false,
          "notNull": false
        },
        "phone": {
          "name": "phone",
          "type": "text",
          "primaryKey": false,
          "notNull": false
        },
        "employee_id": {
          "name": "employee_id",
          "type": "text",
          "primaryKey": false,
          "notNull": false
        },
        "department": {
          "name": "department",
          "type": "text",
          "primaryKey": false,
          "notNull": false
        },
        "position": {
          "name": "position",
          "type": "text",
          "primaryKey": false,
          "notNull": false
        },
        "date_joined": {
          "name": "date_joined",
          "type": "date",
          "primaryKey": false,
          "notNull": false
        },
        "is_active": {
          "name": "is_active",
          "type": "boolean",
          "primaryKey": false,
          "notNull": true,
          "default": true
        },
        "notes": {
          "name": "notes",
          "type": "text",
          "primaryKey": false,
          "notNull": false
        },
        "created_at": {
          "name": "created_at",
          "type": "timestamp with time zone",
          "primaryKey": false,
          "notNull": true,
          "default": "now()"
        },
        "updated_at": {
          "name": "updated_at",
          "type": "timestamp with time zone",
          "primaryKey": false,
          "notNull": true,
          "default": "now()"
        }
      },
      "indexes": {
        "teachers_tenant_idx": {
          "name": "teachers_tenant_idx",
          "columns": [
            {
              "expression": "tenant_id",
              "isExpression": false,
              "asc": true,
              "nulls": "last"
            }
          ],
          "isUnique": false,
          "concurrently": false,
          "method": "btree",
          "with": {}
        },
        "teachers_tenant_email_idx": {
          "name": "teachers_tenant_email_idx",
          "columns": [
            {
              "expression": "tenant_id",
              "isExpression": false,
              "asc": true,
              "nulls": "last"
            },
            {
              "expression": "email",
              "isExpression": false,
              "asc": true,
              "nulls": "last"
            }
          ],
          "isUnique": true,
          "concurrently": false,
          "method": "btree",
          "with": {}
        }
      },
      "foreignKeys": {
        "teachers_tenant_id_tenants_id_fk": {
          "name": "teachers_tenant_id_tenants_id_fk",
          "tableFrom": "teachers",
          "tableTo": "tenants",
          "columnsFrom": [
            "tenant_id"
          ],
          "columnsTo": [
            "id"
          ],
          "onDelete": "cascade",
          "onUpdate": "no action"
        }
      },
      "compositePrimaryKeys": {},
      "uniqueConstraints": {},
      "policies": {},
      "checkConstraints": {},
      "isRLSEnabled": false
    },
    "public.tenant_invites": {
      "name": "tenant_invites",
      "schema": "",
      "columns": {
        "id": {
          "name": "id",
          "type": "uuid",
          "primaryKey": true,
          "notNull": true,
          "default": "gen_random_uuid()"
        },
        "tenant_id": {
          "name": "tenant_id",
          "type": "uuid",
          "primaryKey": false,
          "notNull": true
        },
        "email": {
          "name": "email",
          "type": "text",
          "primaryKey": false,
          "notNull": true
        },
        "role": {
          "name": "role",
          "type": "tenant_role",
          "typeSchema": "public",
          "primaryKey": false,
          "notNull": true,
          "default": "'member'"
        },
        "token": {
          "name": "token",
          "type": "text",
          "primaryKey": false,
          "notNull": true
        },
        "invited_by_id": {
          "name": "invited_by_id",
          "type": "text",
          "primaryKey": false,
          "notNull": true
        },
        "status": {
          "name": "status",
          "type": "invite_status",
          "typeSchema": "public",
          "primaryKey": false,
          "notNull": true,
          "default": "'pending'"
        },
        "expires_at": {
          "name": "expires_at",
          "type": "timestamp with time zone",
          "primaryKey": false,
          "notNull": true
        },
        "accepted_at": {
          "name": "accepted_at",
          "type": "timestamp with time zone",
          "primaryKey": false,
          "notNull": false
        },
        "created_at": {
          "name": "created_at",
          "type": "timestamp with time zone",
          "primaryKey": false,
          "notNull": true,
          "default": "now()"
        }
      },
      "indexes": {
        "tenant_invites_tenant_email_idx": {
          "name": "tenant_invites_tenant_email_idx",
          "columns": [
            {
              "expression": "tenant_id",
              "isExpression": false,
              "asc": true,
              "nulls": "last"
            },
            {
              "expression": "email",
              "isExpression": false,
              "asc": true,
              "nulls": "last"
            }
          ],
          "isUnique": false,
          "concurrently": false,
          "method": "btree",
          "with": {}
        },
        "tenant_invites_token_idx": {
          "name": "tenant_invites_token_idx",
          "columns": [
            {
              "expression": "token",
              "isExpression": false,
              "asc": true,
              "nulls": "last"
            }
          ],
          "isUnique": true,
          "concurrently": false,
          "method": "btree",
          "with": {}
        }
      },
      "foreignKeys": {
        "tenant_invites_tenant_id_tenants_id_fk": {
          "name": "tenant_invites_tenant_id_tenants_id_fk",
          "tableFrom": "tenant_invites",
          "tableTo": "tenants",
          "columnsFrom": [
            "tenant_id"
          ],
          "columnsTo": [
            "id"
          ],
          "onDelete": "cascade",
          "onUpdate": "no action"
        },
        "tenant_invites_invited_by_id_users_id_fk": {
          "name": "tenant_invites_invited_by_id_users_id_fk",
          "tableFrom": "tenant_invites",
          "tableTo": "users",
          "columnsFrom": [
            "invited_by_id"
          ],
          "columnsTo": [
            "id"
          ],
          "onDelete": "cascade",
          "onUpdate": "no action"
        }
      },
      "compositePrimaryKeys": {},
      "uniqueConstraints": {
        "tenant_invites_token_unique": {
          "name": "tenant_invites_token_unique",
          "nullsNotDistinct": false,
          "columns": [
            "token"
          ]
        }
      },
      "policies": {},
      "checkConstraints": {},
      "isRLSEnabled": false
    },
    "public.tenant_members": {
      "name": "tenant_members",
      "schema": "",
      "columns": {
        "tenant_id": {
          "name": "tenant_id",
          "type": "uuid",
          "primaryKey": false,
          "notNull": true
        },
        "user_id": {
          "name": "user_id",
          "type": "text",
          "primaryKey": false,
          "notNull": true
        },
        "role": {
          "name": "role",
          "type": "tenant_role",
          "typeSchema": "public",
          "primaryKey": false,
          "notNull": true,
          "default": "'member'"
        },
        "created_at": {
          "name": "created_at",
          "type": "timestamp with time zone",
          "primaryKey": false,
          "notNull": true,
          "default": "now()"
        }
      },
      "indexes": {
        "tenant_members_user_idx": {
          "name": "tenant_members_user_idx",
          "columns": [
            {
              "expression": "user_id",
              "isExpression": false,
              "asc": true,
              "nulls": "last"
            }
          ],
          "isUnique": false,
          "concurrently": false,
          "method": "btree",
          "with": {}
        }
      },
      "foreignKeys": {
        "tenant_members_tenant_id_tenants_id_fk": {
          "name": "tenant_members_tenant_id_tenants_id_fk",
          "tableFrom": "tenant_members",
          "tableTo": "tenants",
          "columnsFrom": [
            "tenant_id"
          ],
          "columnsTo": [
            "id"
          ],
          "onDelete": "cascade",
          "onUpdate": "no action"
        },
        "tenant_members_user_id_users_id_fk": {
          "name": "tenant_members_user_id_users_id_fk",
          "tableFrom": "tenant_members",
          "tableTo": "users",
          "columnsFrom": [
            "user_id"
          ],
          "columnsTo": [
            "id"
          ],
          "onDelete": "cascade",
          "onUpdate": "no action"
        }
      },
      "compositePrimaryKeys": {
        "tenant_members_tenant_id_user_id_pk": {
          "name": "tenant_members_tenant_id_user_id_pk",
          "columns": [
            "tenant_id",
            "user_id"
          ]
        }
      },
      "uniqueConstraints": {},
      "policies": {},
      "checkConstraints": {},
      "isRLSEnabled": false
    },
    "public.tenants": {
      "name": "tenants",
      "schema": "",
      "columns": {
        "id": {
          "name": "id",
          "type": "uuid",
          "primaryKey": true,
          "notNull": true,
          "default": "gen_random_uuid()"
        },
        "slug": {
          "name": "slug",
          "type": "text",
          "primaryKey": false,
          "notNull": true
        },
        "name": {
          "name": "name",
          "type": "text",
          "primaryKey": false,
          "notNull": true
        },
        "logo_url": {
          "name": "logo_url",
          "type": "text",
          "primaryKey": false,
          "notNull": false
        },
        "country_code": {
          "name": "country_code",
          "type": "text",
          "primaryKey": false,
          "notNull": false
        },
        "created_at": {
          "name": "created_at",
          "type": "timestamp with time zone",
          "primaryKey": false,
          "notNull": true,
          "default": "now()"
        },
        "updated_at": {
          "name": "updated_at",
          "type": "timestamp with time zone",
          "primaryKey": false,
          "notNull": true,
          "default": "now()"
        },
        "deleted_at": {
          "name": "deleted_at",
          "type": "timestamp with time zone",
          "primaryKey": false,
          "notNull": false
        }
      },
      "indexes": {
        "tenants_slug_idx": {
          "name": "tenants_slug_idx",
          "columns": [
            {
              "expression": "slug",
              "isExpression": false,
              "asc": true,
              "nulls": "last"
            }
          ],
          "isUnique": true,
          "concurrently": false,
          "method": "btree",
          "with": {}
        }
      },
      "foreignKeys": {},
      "compositePrimaryKeys": {},
      "uniqueConstraints": {
        "tenants_slug_unique": {
          "name": "tenants_slug_unique",
          "nullsNotDistinct": false,
          "columns": [
            "slug"
          ]
        }
      },
      "policies": {},
      "checkConstraints": {},
      "isRLSEnabled": false
    },
    "public.uploads": {
      "name": "uploads",
      "schema": "",
      "columns": {
        "id": {
          "name": "id",
          "type": "uuid",
          "primaryKey": true,
          "notNull": true,
          "default": "gen_random_uuid()"
        },
        "tenant_id": {
          "name": "tenant_id",
          "type": "uuid",
          "primaryKey": false,
          "notNull": true
        },
        "uploaded_by_id": {
          "name": "uploaded_by_id",
          "type": "text",
          "primaryKey": false,
          "notNull": true
        },
        "exam_type": {
          "name": "exam_type",
          "type": "exam_type",
          "typeSchema": "public",
          "primaryKey": false,
          "notNull": true
        },
        "month": {
          "name": "month",
          "type": "text",
          "primaryKey": false,
          "notNull": true
        },
        "year": {
          "name": "year",
          "type": "integer",
          "primaryKey": false,
          "notNull": true
        },
        "file_name": {
          "name": "file_name",
          "type": "text",
          "primaryKey": false,
          "notNull": true
        },
        "file_size": {
          "name": "file_size",
          "type": "integer",
          "primaryKey": false,
          "notNull": true
        },
        "file_format": {
          "name": "file_format",
          "type": "text",
          "primaryKey": false,
          "notNull": true
        },
        "status": {
          "name": "status",
          "type": "upload_status",
          "typeSchema": "public",
          "primaryKey": false,
          "notNull": true,
          "default": "'processing'"
        },
        "record_count": {
          "name": "record_count",
          "type": "integer",
          "primaryKey": false,
          "notNull": true,
          "default": 0
        },
        "error_message": {
          "name": "error_message",
          "type": "text",
          "primaryKey": false,
          "notNull": false
        },
        "credits_charged": {
          "name": "credits_charged",
          "type": "integer",
          "primaryKey": false,
          "notNull": true,
          "default": 1
        },
        "credit_transaction_id": {
          "name": "credit_transaction_id",
          "type": "uuid",
          "primaryKey": false,
          "notNull": false
        },
        "period": {
          "name": "period",
          "type": "date",
          "primaryKey": false,
          "notNull": false
        },
        "processed_at": {
          "name": "processed_at",
          "type": "timestamp with time zone",
          "primaryKey": false,
          "notNull": false
        },
        "created_at": {
          "name": "created_at",
          "type": "timestamp with time zone",
          "primaryKey": false,
          "notNull": true,
          "default": "now()"
        }
      },
      "indexes": {
        "uploads_tenant_idx": {
          "name": "uploads_tenant_idx",
          "columns": [
            {
              "expression": "tenant_id",
              "isExpression": false,
              "asc": true,
              "nulls": "last"
            },
            {
              "expression": "created_at",
              "isExpression": false,
              "asc": true,
              "nulls": "last"
            }
          ],
          "isUnique": false,
          "concurrently": false,
          "method": "btree",
          "with": {}
        },
        "uploads_tenant_period_idx": {
          "name": "uploads_tenant_period_idx",
          "columns": [
            {
              "expression": "tenant_id",
              "isExpression": false,
              "asc": true,
              "nulls": "last"
            },
            {
              "expression": "period",
              "isExpression": false,
              "asc": true,
              "nulls": "last"
            },
            {
              "expression": "exam_type",
              "isExpression": false,
              "asc": true,
              "nulls": "last"
            }
          ],
          "isUnique": false,
          "concurrently": false,
          "method": "btree",
          "with": {}
        }
      },
      "foreignKeys": {
        "uploads_tenant_id_tenants_id_fk": {
          "name": "uploads_tenant_id_tenants_id_fk",
          "tableFrom": "uploads",
          "tableTo": "tenants",
          "columnsFrom": [
            "tenant_id"
          ],
          "columnsTo": [
            "id"
          ],
          "onDelete": "cascade",
          "onUpdate": "no action"
        },
        "uploads_uploaded_by_id_users_id_fk": {
          "name": "uploads_uploaded_by_id_users_id_fk",
          "tableFrom": "uploads",
          "tableTo": "users",
          "columnsFrom": [
            "uploaded_by_id"
          ],
          "columnsTo": [
            "id"
          ],
          "onDelete": "set null",
          "onUpdate": "no action"
        },
        "uploads_credit_transaction_id_credit_transactions_id_fk": {
          "name": "uploads_credit_transaction_id_credit_transactions_id_fk",
          "tableFrom": "uploads",
          "tableTo": "credit_transactions",
          "columnsFrom": [
            "credit_transaction_id"
          ],
          "columnsTo": [
            "id"
          ],
          "onDelete": "set null",
          "onUpdate": "no action"
        }
      },
      "compositePrimaryKeys": {},
      "uniqueConstraints": {},
      "policies": {},
      "checkConstraints": {},
      "isRLSEnabled": false
    },
    "public.users": {
      "name": "users",
      "schema": "",
      "columns": {
        "id": {
          "name": "id",
          "type": "text",
          "primaryKey": true,
          "notNull": true
        },
        "email": {
          "name": "email",
          "type": "text",
          "primaryKey": false,
          "notNull": true
        },
        "name": {
          "name": "name",
          "type": "text",
          "primaryKey": false,
          "notNull": false
        },
        "image": {
          "name": "image",
          "type": "text",
          "primaryKey": false,
          "notNull": false
        },
        "email_verified": {
          "name": "email_verified",
          "type": "boolean",
          "primaryKey": false,
          "notNull": true,
          "default": false
        },
        "is_super_admin": {
          "name": "is_super_admin",
          "type": "boolean",
          "primaryKey": false,
          "notNull": true,
          "default": false
        },
        "created_at": {
          "name": "created_at",
          "type": "timestamp with time zone",
          "primaryKey": false,
          "notNull": true,
          "default": "now()"
        },
        "updated_at": {
          "name": "updated_at",
          "type": "timestamp with time zone",
          "primaryKey": false,
          "notNull": true,
          "default": "now()"
        }
      },
      "indexes": {
        "users_email_idx": {
          "name": "users_email_idx",
          "columns": [
            {
              "expression": "email",
              "isExpression": false,
              "asc": true,
              "nulls": "last"
            }
          ],
          "isUnique": false,
          "concurrently": false,
          "method": "btree",
          "with": {}
        }
      },
      "foreignKeys": {},
      "compositePrimaryKeys": {},
      "uniqueConstraints": {
        "users_email_unique": {
          "name": "users_email_unique",
          "nullsNotDistinct": false,
          "columns": [
            "email"
          ]
        }
      },
      "policies": {},
      "checkConstraints": {},
      "isRLSEnabled": false
    },
    "public.verifications": {
      "name": "verifications",
      "schema": "",
      "columns": {
        "id": {
          "name": "id",
          "type": "text",
          "primaryKey": true,
          "notNull": true
        },
        "identifier": {
          "name": "identifier",
          "type": "text",
          "primaryKey": false,
          "notNull": true
        },
        "value": {
          "name": "value",
          "type": "text",
          "primaryKey": false,
          "notNull": true
        },
        "expires_at": {
          "name": "expires_at",
          "type": "timestamp with time zone",
          "primaryKey": false,
          "notNull": true
        },
        "created_at": {
          "name": "created_at",
          "type": "timestamp with time zone",
          "primaryKey": false,
          "notNull": true,
          "default": "now()"
        },
        "updated_at": {
          "name": "updated_at",
          "type": "timestamp with time zone",
          "primaryKey": false,
          "notNull": true,
          "default": "now()"
        }
      },
      "indexes": {},
      "foreignKeys": {},
      "compositePrimaryKeys": {},
      "uniqueConstraints": {},
      "policies": {},
      "checkConstraints": {},
      "isRLSEnabled": false
    }
  },
  "enums": {
    "public.credit_txn_type": {
      "name": "credit_txn_type",
      "schema": "public",
      "values": [
        "purchase",
        "upload",
        "refund",
        "admin_grant",
        "admin_revoke"
      ]
    },
    "public.exam_type": {
      "name": "exam_type",
      "schema": "public",
      "values": [
        "IGCSE",
        "A Level"
      ]
    },
    "public.invite_status": {
      "name": "invite_status",
      "schema": "public",
      "values": [
        "pending",
        "accepted",
        "revoked",
        "expired"
      ]
    },
    "public.purchase_status": {
      "name": "purchase_status",
      "schema": "public",
      "values": [
        "initialized",
        "pending",
        "success",
        "failed",
        "abandoned"
      ]
    },
    "public.tenant_role": {
      "name": "tenant_role",
      "schema": "public",
      "values": [
        "owner",
        "admin",
        "member"
      ]
    },
    "public.upload_status": {
      "name": "upload_status",
      "schema": "public",
      "values": [
        "processing",
        "processed",
        "failed"
      ]
    }
  },
  "schemas": {},
  "sequences": {},
  "roles": {},
  "policies": {},
  "views": {},
  "_meta": {
    "columns": {},
    "schemas": {},
    "tables": {}
  }
}